[
    {
        "team": "横浜DeNAベイスターズ",
        "name": "浜地　真澄",
        "number": 52
    },
    {
        "team": "横浜DeNAベイスターズ",
        "name": "清水　麻成",
        "number": 102
    },
    {
        "team": "横浜DeNAベイスターズ",
        "name": "金渕　光希",
        "number": 103
    },
    {
        "team": "横浜DeNAベイスターズ",
        "name": "吉岡　暖",
        "number": 111
    },
    {
        "team": "横浜DeNAベイスターズ",
        "name": "馬場　皐輔",
        "number": 115
    },
    {
        "team": "横浜DeNAベイスターズ",
        "name": "森下　瑠大",
        "number": 136
    },
    {
        "team": "横浜DeNAベイスターズ",
        "name": "松本　隆之介",
        "number": 140
    },
    {
        "team": "横浜DeNAベイスターズ",
        "name": "上甲　凌大",
        "number": 127
    },
    {
        "team": "横浜DeNAベイスターズ",
        "name": "近藤　大雅",
        "number": 130
    },
    {
        "team": "横浜DeNAベイスターズ",
        "name": "小笠原　蒼",
        "number": 125
    },
    {
        "team": "横浜DeNAベイスターズ",
        "name": "西巻　賢二",
        "number": 129
    },
    {
        "team": "横浜DeNAベイスターズ",
        "name": "清水　詩太",
        "number": 131
    },
    {
        "team": "横浜DeNAベイスターズ",
        "name": "高見澤　郁魅",
        "number": 193
    },
    {
        "team": "横浜DeNAベイスターズ",
        "name": "小針　大輝",
        "number": 155
    }
]